alibabacloud_ecs20140526/__init__.py
alibabacloud_ecs20140526/client.py
alibabacloud_ecs20140526/models/__init__.py
alibabacloud_ecs20140526/models/_accept_inquired_system_event_request.py
alibabacloud_ecs20140526/models/_accept_inquired_system_event_response.py
alibabacloud_ecs20140526/models/_accept_inquired_system_event_response_body.py
alibabacloud_ecs20140526/models/_activate_router_interface_request.py
alibabacloud_ecs20140526/models/_activate_router_interface_response.py
alibabacloud_ecs20140526/models/_activate_router_interface_response_body.py
alibabacloud_ecs20140526/models/_add_bandwidth_package_ips_request.py
alibabacloud_ecs20140526/models/_add_bandwidth_package_ips_response.py
alibabacloud_ecs20140526/models/_add_bandwidth_package_ips_response_body.py
alibabacloud_ecs20140526/models/_add_tags_request.py
alibabacloud_ecs20140526/models/_add_tags_response.py
alibabacloud_ecs20140526/models/_add_tags_response_body.py
alibabacloud_ecs20140526/models/_allocate_dedicated_hosts_request.py
alibabacloud_ecs20140526/models/_allocate_dedicated_hosts_response.py
alibabacloud_ecs20140526/models/_allocate_dedicated_hosts_response_body.py
alibabacloud_ecs20140526/models/_allocate_eip_address_request.py
alibabacloud_ecs20140526/models/_allocate_eip_address_response.py
alibabacloud_ecs20140526/models/_allocate_eip_address_response_body.py
alibabacloud_ecs20140526/models/_allocate_public_ip_address_request.py
alibabacloud_ecs20140526/models/_allocate_public_ip_address_response.py
alibabacloud_ecs20140526/models/_allocate_public_ip_address_response_body.py
alibabacloud_ecs20140526/models/_apply_auto_snapshot_policy_request.py
alibabacloud_ecs20140526/models/_apply_auto_snapshot_policy_response.py
alibabacloud_ecs20140526/models/_apply_auto_snapshot_policy_response_body.py
alibabacloud_ecs20140526/models/_assign_ipv_6addresses_request.py
alibabacloud_ecs20140526/models/_assign_ipv_6addresses_response.py
alibabacloud_ecs20140526-7.5.4.dist-info/LICENSE
alibabacloud_ecs20140526-7.5.4.dist-info/METADATA
alibabacloud_ecs20140526-7.5.4.dist-info/WHEEL
alibabacloud_ecs20140526-7.5.4.dist-info/top_level.txt
alibabacloud_ecs20140526-7.5.4.dist-info/RECORD
